spark_jira_tools/__init__.py
spark_jira_tools/functions/__init__.py
spark_jira_tools/functions/generator.py
spark_jira_tools/utils/__init__.py
spark_jira_tools/utils/color.py
spark_jira_tools/utils/jira.py
spark_jira_tools/utils/resource/__init__.py
spark_jira_tools/utils/resource/jira_task.csv
spark_jira_tools/utils/resource/jira_task2.csv
spark_jira_tools-0.4.4.dist-info/LICENSE
spark_jira_tools-0.4.4.dist-info/METADATA
spark_jira_tools-0.4.4.dist-info/WHEEL
spark_jira_tools-0.4.4.dist-info/top_level.txt
spark_jira_tools-0.4.4.dist-info/RECORD
