Metadata-Version: 2.1
Name: spark-jira-tools
Version: 0.4.4
Summary: spark_jira_tools
Home-page: https://github.com/jonaqp/spark_jira_tools/
Author: Jonathan Quiza
Author-email: jony327@gmail.com
License: UNKNOWN
Download-URL: https://github.com/jonaqp/spark_jira_tools/archive/main.zip
Keywords: spark,jira,bitbucket
Platform: UNKNOWN
Classifier: Development Status :: 5 - Production/Stable
Classifier: Intended Audience :: Developers
Classifier: Intended Audience :: Science/Research
Classifier: Topic :: Scientific/Engineering :: Artificial Intelligence
Classifier: License :: OSI Approved :: Apache Software License
Classifier: Programming Language :: Python :: 3.9
License-File: LICENSE
Requires-Dist: pandas (==2.0.1)
Requires-Dist: numpy (==1.24.3)
Requires-Dist: pyarrow (==12.0.0)
Requires-Dist: setuptools (==58.2.0)
Requires-Dist: wheel (==0.40.0)
Requires-Dist: color-tools (>=0.0.2)
Requires-Dist: itables (==1.5.3)
Requires-Dist: prettytable (==3.8.0)
Requires-Dist: jupyterlab (==4.0.5)
